ergast/__init__.py
ergast/client.py
ergast/formatter.py
ergast/request.py
ergast/seasons.py
ergast-0.0.4.dist-info/DESCRIPTION.rst
ergast-0.0.4.dist-info/METADATA
ergast-0.0.4.dist-info/RECORD
ergast-0.0.4.dist-info/WHEEL
ergast-0.0.4.dist-info/metadata.json
ergast-0.0.4.dist-info/top_level.txt
test/__init__.py
test/test_request.py
