Metadata-Version: 2.0
Name: ergast
Version: 0.0.4
Summary: Python HTTP client to the Ergast Motor Racing Data API
Home-page: http://github.com/nackjicholson/ergast-python
Author: Will Vaughn
Author-email: willieviseoae@gmail.com
License: MIT
Keywords: ergast formula1 racing motorsports http client
Platform: UNKNOWN
Requires-Dist: Cerberus (==1.1)
Requires-Dist: requests (==2.16.5)
Requires-Dist: six
Requires-Dist: uritemplate (==3.0.0)
